tablign/__about__.py
tablign/__init__.py
tablign/cli.py
tablign/main.py
tablign-0.3.7.dist-info/LICENSE
tablign-0.3.7.dist-info/METADATA
tablign-0.3.7.dist-info/WHEEL
tablign-0.3.7.dist-info/entry_points.txt
tablign-0.3.7.dist-info/top_level.txt
tablign-0.3.7.dist-info/RECORD
